mtko/__init__.py
mtko/env_setup.py
mtko/history.py
mtko/main.py
mtko/query.py
mtko-0.1.7.dist-info/LICENSE
mtko-0.1.7.dist-info/METADATA
mtko-0.1.7.dist-info/WHEEL
mtko-0.1.7.dist-info/entry_points.txt
mtko-0.1.7.dist-info/top_level.txt
mtko-0.1.7.dist-info/RECORD
