Metadata-Version: 2.1
Name: mtko
Version: 0.1.7
Summary: A CLI tool for sending commands, error messages, tracebacks, and file contents directly to OpenAI GPT models without leaving your terminal.
Home-page: https://github.com/palmtreeshinobi/mtko/
Author: Van
License: MIT
Project-URL: Source Code, https://github.com/palmtreeshinobi/mtko/
Platform: UNKNOWN
Classifier: Programming Language :: Python :: 3
Classifier: License :: OSI Approved :: MIT License
Classifier: Operating System :: OS Independent
Requires-Python: >=3.6
License-File: LICENSE
Requires-Dist: openai
Requires-Dist: python-dotenv
